roleplaycog/__init__.py
roleplaycog/roleplay.py
roleplaycog-1.0.2.dist-info/LICENCE.md
roleplaycog-1.0.2.dist-info/METADATA
roleplaycog-1.0.2.dist-info/WHEEL
roleplaycog-1.0.2.dist-info/top_level.txt
roleplaycog-1.0.2.dist-info/RECORD
