Metadata-Version: 2.1
Name: roleplaycog
Version: 1.0.2
Summary: Roleplay cog for py-cord
Home-page: https://github.com/mariohero24/roleplaycog
Author: Guard Boi
Author-email: guard@cowbot.xyz
Classifier: Programming Language :: Python :: 3
Classifier: License :: OSI Approved :: MIT License
Classifier: Operating System :: OS Independent
Requires-Python: >=3.8
License-File: LICENCE.md
